ascii_library/__init__.py
ascii_library/cleanup/__init__.py
ascii_library/cleanup/id_namespaces.py
ascii_library/cleanup/orbis_seeds.py
ascii_library/cleanup/commoncrawl/__init__.py
ascii_library/cleanup/commoncrawl/text_extraction.py
ascii_library/cleanup/commoncrawl/urls.py
ascii_library/cleanup/commoncrawl/utils_logging.py
ascii_library/cleanup/commoncrawl/warc_handling.py
ascii_library/cleanup/schema/__init__.py
ascii_library/cleanup/schema/basics.py
ascii_library/cleanup/utils/__init__.py
ascii_library/cleanup/utils/hs_code_description_matching.py
ascii_library/models/__init__.py
ascii_library/models/defaults.py
ascii_library/orchestration/__init__.py
ascii_library/orchestration/dbt_translator.py
ascii_library/orchestration/pipes/__init__.py
ascii_library/orchestration/pipes/cloud_client.py
ascii_library/orchestration/pipes/databricks.py
ascii_library/orchestration/pipes/emr.py
ascii_library/orchestration/pipes/exceptions.py
ascii_library/orchestration/pipes/instance_config.py
ascii_library/orchestration/pipes/io_paths_cc.py
ascii_library/orchestration/pipes/spark_pipes.py
ascii_library/orchestration/pipes/spark_pipes_factory.py
ascii_library/orchestration/pipes/spark_script_abc.py
ascii_library/orchestration/pipes/utils.py
ascii_library/orchestration/resources/__init__.py
ascii_library/orchestration/resources/constants.py
ascii_library/orchestration/resources/databricks.py
ascii_library/orchestration/resources/emr.py
ascii_library/orchestration/resources/emr_constants.py
ascii_library/orchestration/resources/parquet_io_manager.py
ascii_library/orchestration/resources/spark.py
ascii_library/orchestration/resources/utils.py
ascii_library/resources/__init__.py
ascii_library/resources/configurable_dbt.py
ascii_library/resources/duckdb_file.py
ascii_library/resources/duckdb_protocol.py
ascii_library/resources/ducklake.py
ascii_library/resources/lazy_local_ray.py
ascii_library/resources/obstore_s3.py
ascii_library/sensors/__init__.py
ascii_library-1.2.42.dist-info/licenses/LICENSE
ascii_library-1.2.42.dist-info/METADATA
ascii_library-1.2.42.dist-info/WHEEL
ascii_library-1.2.42.dist-info/top_level.txt
ascii_library-1.2.42.dist-info/RECORD
